{
	"name": "Lvl-2",
	"layers": [
		{
			"name": "Background",
			"overriden": 0,
			"subLayers": [],
			"instances": [
				{
					"type": "Background",
					"properties": {
						"initially-visible": true,
						"origin": "bottom",
						"wrap-horizontal": "repeat",
						"wrap-vertical": "repeat",
						"image-offset-x": 0,
						"image-offset-y": 0,
						"image-scale-x": 1,
						"image-scale-y": 1,
						"image-angle": 0,
						"enable-tile-randomization": false,
						"x-random": 1,
						"y-random": 1,
						"angle-random": 1,
						"blend-margin-x": 0.1,
						"blend-margin-y": 0.1
					},
					"uid": 72,
					"sid": 540519452975311,
					"tags": "",
					"instanceVariables": {},
					"behaviors": {},
					"instanceFolderItem": {
						"sid": 540519452975311,
						"expanded": true,
						"folderName": "",
						"indexInFolder": -1,
						"folderNestingLevel": -1
					},
					"showing": true,
					"locked": false,
					"world": {
						"x": 360,
						"y": 1280,
						"width": 720,
						"height": 1280,
						"originX": 0.5,
						"originY": 1,
						"color": [
							1,
							1,
							1,
							0.8
						],
						"angle": 0,
						"zElevation": 0
					}
				}
			],
			"sid": 935447001286820,
			"effectTypes": [],
			"isInitiallyVisible": true,
			"isInitiallyInteractive": true,
			"isHTMLElementsLayer": false,
			"color": [
				1,
				1,
				1,
				1
			],
			"backgroundColor": [
				1,
				1,
				1,
				1
			],
			"isTransparent": false,
			"parallaxX": 0,
			"parallaxY": 1,
			"scaleRate": 1,
			"forceOwnTexture": false,
			"renderingMode": "3d",
			"drawOrder": "z-order",
			"useRenderCells": false,
			"blendMode": "normal",
			"zElevation": 0,
			"global": false
		},
		{
			"name": "Texture",
			"overriden": 0,
			"subLayers": [],
			"instances": [
				{
					"type": "Texture",
					"properties": {
						"initially-visible": true,
						"origin": "top-left",
						"wrap-horizontal": "repeat",
						"wrap-vertical": "repeat",
						"image-offset-x": 0,
						"image-offset-y": 0,
						"image-scale-x": 0.7,
						"image-scale-y": 0.7,
						"image-angle": 0,
						"enable-tile-randomization": false,
						"x-random": 1,
						"y-random": 1,
						"angle-random": 1,
						"blend-margin-x": 0.1,
						"blend-margin-y": 0.1
					},
					"uid": 73,
					"sid": 693085691102817,
					"tags": "",
					"instanceVariables": {},
					"behaviors": {},
					"effects": {
						"BetterOutline": {
							"isEnabled": false,
							"parameters": {
								"color": [
									0.36470588235294116,
									0.23529411764705882,
									0.2196078431372549,
									1
								],
								"width": 4,
								"precision-step": 1,
								"samples": 16
							}
						}
					},
					"instanceFolderItem": {
						"sid": 693085691102817,
						"expanded": true,
						"folderName": "",
						"indexInFolder": -1,
						"folderNestingLevel": -1
					},
					"showing": true,
					"locked": false,
					"world": {
						"x": 140,
						"y": 928,
						"width": 440,
						"height": 352,
						"originX": 0,
						"originY": 0,
						"color": [
							1,
							1,
							1,
							1
						],
						"angle": 0,
						"zElevation": 0
					}
				}
			],
			"sid": 518864981396736,
			"effectTypes": [],
			"isInitiallyVisible": true,
			"isInitiallyInteractive": true,
			"isHTMLElementsLayer": false,
			"color": [
				1,
				1,
				1,
				1
			],
			"backgroundColor": [
				1,
				1,
				1,
				1
			],
			"isTransparent": true,
			"parallaxX": 0,
			"parallaxY": 1,
			"scaleRate": 1,
			"forceOwnTexture": false,
			"renderingMode": "3d",
			"drawOrder": "z-order",
			"useRenderCells": false,
			"blendMode": "normal",
			"zElevation": 0,
			"global": false
		},
		{
			"name": "Texture Eracer",
			"overriden": 0,
			"subLayers": [],
			"instances": [],
			"sid": 715265176483293,
			"effectTypes": [],
			"isInitiallyVisible": true,
			"isInitiallyInteractive": true,
			"isHTMLElementsLayer": false,
			"color": [
				1,
				1,
				1,
				1
			],
			"backgroundColor": [
				1,
				1,
				1,
				1
			],
			"isTransparent": true,
			"parallaxX": 0,
			"parallaxY": 1,
			"scaleRate": 1,
			"forceOwnTexture": false,
			"renderingMode": "3d",
			"drawOrder": "z-order",
			"useRenderCells": false,
			"blendMode": "normal",
			"zElevation": 0,
			"global": false
		},
		{
			"name": "Canvas",
			"overriden": 0,
			"subLayers": [],
			"instances": [
				{
					"type": "DrawingCanvas",
					"properties": {
						"resolution-mode": "auto",
						"initially-visible": true,
						"origin": "top-left",
						"antialiasing": "4x-msaa"
					},
					"uid": 80,
					"sid": 692842494176401,
					"tags": "",
					"instanceVariables": {},
					"behaviors": {
						"Pin": {
							"properties": {
								"destroy": false
							}
						}
					},
					"effects": {
						"BetterOutline": {
							"isEnabled": true,
							"parameters": {
								"color": [
									0.36470588235294116,
									0.23529411764705882,
									0.2196078431372549,
									1
								],
								"width": 4,
								"precision-step": 1,
								"samples": 16
							}
						}
					},
					"showing": true,
					"locked": false,
					"world": {
						"x": 0,
						"y": 0,
						"width": 720,
						"height": 1280,
						"originX": 0,
						"originY": 0,
						"color": [
							1,
							1,
							1,
							1
						],
						"angle": 0,
						"zElevation": 0
					}
				}
			],
			"sid": 125664520011479,
			"effectTypes": [],
			"isInitiallyVisible": true,
			"isInitiallyInteractive": true,
			"isHTMLElementsLayer": false,
			"color": [
				1,
				1,
				1,
				1
			],
			"backgroundColor": [
				1,
				1,
				1,
				1
			],
			"isTransparent": true,
			"parallaxX": 0,
			"parallaxY": 1,
			"scaleRate": 1,
			"forceOwnTexture": false,
			"renderingMode": "3d",
			"drawOrder": "z-order",
			"useRenderCells": false,
			"blendMode": "normal",
			"zElevation": 0,
			"global": false
		},
		{
			"name": "Drawing area",
			"overriden": 0,
			"subLayers": [],
			"instances": [
				{
					"type": "Paper",
					"properties": {
						"initially-visible": true,
						"origin": "top-left",
						"wrap-horizontal": "repeat",
						"wrap-vertical": "repeat",
						"image-offset-x": 0,
						"image-offset-y": 0,
						"image-scale-x": 1,
						"image-scale-y": 1,
						"image-angle": 0,
						"enable-tile-randomization": false,
						"x-random": 1,
						"y-random": 1,
						"angle-random": 1,
						"blend-margin-x": 0.1,
						"blend-margin-y": 0.1
					},
					"uid": 81,
					"sid": 969365442768957,
					"tags": "",
					"instanceVariables": {},
					"behaviors": {},
					"instanceFolderItem": {
						"sid": 969365442768957,
						"expanded": true,
						"folderName": "",
						"indexInFolder": -1,
						"folderNestingLevel": -1
					},
					"showing": true,
					"locked": false,
					"world": {
						"x": 69,
						"y": 225,
						"width": 582,
						"height": 392,
						"originX": 0,
						"originY": 0,
						"color": [
							1,
							1,
							1,
							1
						],
						"angle": 0,
						"zElevation": 0
					}
				},
				{
					"type": "DashedLine",
					"properties": {
						"initially-visible": true,
						"origin": "left",
						"wrap-horizontal": "repeat",
						"wrap-vertical": "clamp-to-edge",
						"image-offset-x": 0,
						"image-offset-y": 0,
						"image-scale-x": 1,
						"image-scale-y": 1,
						"image-angle": 0,
						"enable-tile-randomization": false,
						"x-random": 1,
						"y-random": 1,
						"angle-random": 1,
						"blend-margin-x": 0.1,
						"blend-margin-y": 0.1
					},
					"uid": 82,
					"sid": 895092594321982,
					"tags": "",
					"instanceVariables": {},
					"behaviors": {},
					"instanceFolderItem": {
						"sid": 895092594321982,
						"expanded": true,
						"folderName": "",
						"indexInFolder": -1,
						"folderNestingLevel": -1
					},
					"showing": true,
					"locked": false,
					"world": {
						"x": 79,
						"y": 617,
						"width": 562,
						"height": 14,
						"originX": 0,
						"originY": 0.5,
						"color": [
							1,
							1,
							1,
							1
						],
						"angle": 0,
						"zElevation": 0
					}
				},
				{
					"type": "DashedLine",
					"properties": {
						"initially-visible": true,
						"origin": "left",
						"wrap-horizontal": "repeat",
						"wrap-vertical": "clamp-to-edge",
						"image-offset-x": 0,
						"image-offset-y": 0,
						"image-scale-x": 1,
						"image-scale-y": 1,
						"image-angle": 0,
						"enable-tile-randomization": false,
						"x-random": 1,
						"y-random": 1,
						"angle-random": 1,
						"blend-margin-x": 0.1,
						"blend-margin-y": 0.1
					},
					"uid": 83,
					"sid": 726671091370224,
					"tags": "",
					"instanceVariables": {},
					"behaviors": {},
					"instanceFolderItem": {
						"sid": 726671091370224,
						"expanded": true,
						"folderName": "",
						"indexInFolder": -1,
						"folderNestingLevel": -1
					},
					"showing": true,
					"locked": false,
					"world": {
						"x": 69,
						"y": 607,
						"width": 372,
						"height": 14,
						"originX": 0,
						"originY": 0.5,
						"color": [
							1,
							1,
							1,
							1
						],
						"angle": 4.71238898038469,
						"zElevation": 0
					}
				},
				{
					"type": "DashedLine",
					"properties": {
						"initially-visible": true,
						"origin": "left",
						"wrap-horizontal": "repeat",
						"wrap-vertical": "clamp-to-edge",
						"image-offset-x": 0,
						"image-offset-y": 0,
						"image-scale-x": 1,
						"image-scale-y": 1,
						"image-angle": 0,
						"enable-tile-randomization": false,
						"x-random": 1,
						"y-random": 1,
						"angle-random": 1,
						"blend-margin-x": 0.1,
						"blend-margin-y": 0.1
					},
					"uid": 84,
					"sid": 373871021152393,
					"tags": "",
					"instanceVariables": {},
					"behaviors": {},
					"instanceFolderItem": {
						"sid": 373871021152393,
						"expanded": true,
						"folderName": "",
						"indexInFolder": -1,
						"folderNestingLevel": -1
					},
					"showing": true,
					"locked": false,
					"world": {
						"x": 79,
						"y": 225,
						"width": 562,
						"height": 14,
						"originX": 0,
						"originY": 0.5,
						"color": [
							1,
							1,
							1,
							1
						],
						"angle": 0,
						"zElevation": 0
					}
				},
				{
					"type": "DashedLine",
					"properties": {
						"initially-visible": true,
						"origin": "left",
						"wrap-horizontal": "repeat",
						"wrap-vertical": "clamp-to-edge",
						"image-offset-x": 0,
						"image-offset-y": 0,
						"image-scale-x": 1,
						"image-scale-y": 1,
						"image-angle": 0,
						"enable-tile-randomization": false,
						"x-random": 1,
						"y-random": 1,
						"angle-random": 1,
						"blend-margin-x": 0.1,
						"blend-margin-y": 0.1
					},
					"uid": 85,
					"sid": 334425341899606,
					"tags": "",
					"instanceVariables": {},
					"behaviors": {},
					"instanceFolderItem": {
						"sid": 334425341899606,
						"expanded": true,
						"folderName": "",
						"indexInFolder": -1,
						"folderNestingLevel": -1
					},
					"showing": true,
					"locked": false,
					"world": {
						"x": 651,
						"y": 607,
						"width": 372,
						"height": 14,
						"originX": 0,
						"originY": 0.5,
						"color": [
							1,
							1,
							1,
							1
						],
						"angle": 4.71238898038469,
						"zElevation": 0
					}
				}
			],
			"sid": 649510728038420,
			"effectTypes": [],
			"isInitiallyVisible": true,
			"isInitiallyInteractive": true,
			"isHTMLElementsLayer": false,
			"color": [
				1,
				1,
				1,
				1
			],
			"backgroundColor": [
				1,
				1,
				1,
				1
			],
			"isTransparent": true,
			"parallaxX": 0,
			"parallaxY": 1,
			"scaleRate": 1,
			"forceOwnTexture": false,
			"renderingMode": "3d",
			"drawOrder": "z-order",
			"useRenderCells": false,
			"blendMode": "normal",
			"zElevation": 0,
			"global": false
		},
		{
			"name": "Hints",
			"overriden": 0,
			"subLayers": [],
			"instances": [
				{
					"type": "Hint",
					"properties": {
						"left-margin": 5,
						"right-margin": 5,
						"top-margin": 0,
						"bottom-margin": 0,
						"edges": "tile",
						"fill": "stretch",
						"initially-visible": false,
						"origin": "left",
						"seams": "exact"
					},
					"uid": 86,
					"sid": 992630315486505,
					"tags": "",
					"instanceVariables": {},
					"behaviors": {
						"Tween": {
							"properties": {
								"enabled": true
							}
						}
					},
					"instanceFolderItem": {
						"sid": 992630315486505,
						"expanded": true,
						"folderName": "",
						"indexInFolder": -1,
						"folderNestingLevel": -1
					},
					"showing": true,
					"locked": false,
					"world": {
						"x": 187,
						"y": 310,
						"width": 334,
						"height": 10,
						"originX": 0,
						"originY": 0.5,
						"color": [
							0.11764705882352941,
							0.11764705882352941,
							0.11764705882352941,
							1
						],
						"angle": 0,
						"zElevation": 0
					}
				},
				{
					"type": "Hint",
					"properties": {
						"left-margin": 5,
						"right-margin": 5,
						"top-margin": 0,
						"bottom-margin": 0,
						"edges": "tile",
						"fill": "stretch",
						"initially-visible": false,
						"origin": "left",
						"seams": "exact"
					},
					"uid": 87,
					"sid": 241741457297260,
					"tags": "",
					"instanceVariables": {},
					"behaviors": {
						"Tween": {
							"properties": {
								"enabled": true
							}
						}
					},
					"instanceFolderItem": {
						"sid": 241741457297260,
						"expanded": true,
						"folderName": "",
						"indexInFolder": -1,
						"folderNestingLevel": -1
					},
					"showing": true,
					"locked": false,
					"world": {
						"x": 516,
						"y": 305,
						"width": 232,
						"height": 10,
						"originX": 0,
						"originY": 0.5,
						"color": [
							0.11764705882352941,
							0.11764705882352941,
							0.11764705882352941,
							1
						],
						"angle": 1.5707963267948966,
						"zElevation": 0
					}
				},
				{
					"type": "Hint",
					"properties": {
						"left-margin": 5,
						"right-margin": 5,
						"top-margin": 0,
						"bottom-margin": 0,
						"edges": "tile",
						"fill": "stretch",
						"initially-visible": false,
						"origin": "left",
						"seams": "exact"
					},
					"uid": 88,
					"sid": 720538400806152,
					"tags": "",
					"instanceVariables": {},
					"behaviors": {
						"Tween": {
							"properties": {
								"enabled": true
							}
						}
					},
					"instanceFolderItem": {
						"sid": 720538400806152,
						"expanded": true,
						"folderName": "",
						"indexInFolder": -1,
						"folderNestingLevel": -1
					},
					"showing": true,
					"locked": false,
					"world": {
						"x": 521,
						"y": 532,
						"width": 334,
						"height": 10,
						"originX": 0,
						"originY": 0.5,
						"color": [
							0.11764705882352941,
							0.11764705882352941,
							0.11764705882352941,
							1
						],
						"angle": 3.141592653589793,
						"zElevation": 0
					}
				},
				{
					"type": "Hint",
					"properties": {
						"left-margin": 5,
						"right-margin": 5,
						"top-margin": 0,
						"bottom-margin": 0,
						"edges": "tile",
						"fill": "stretch",
						"initially-visible": false,
						"origin": "left",
						"seams": "exact"
					},
					"uid": 74,
					"sid": 233688997401748,
					"tags": "",
					"instanceVariables": {},
					"behaviors": {
						"Tween": {
							"properties": {
								"enabled": true
							}
						}
					},
					"instanceFolderItem": {
						"sid": 233688997401748,
						"expanded": true,
						"folderName": "",
						"indexInFolder": -1,
						"folderNestingLevel": -1
					},
					"showing": true,
					"locked": false,
					"world": {
						"x": 192,
						"y": 537,
						"width": 232,
						"height": 10,
						"originX": 0,
						"originY": 0.5,
						"color": [
							0.11764705882352941,
							0.11764705882352941,
							0.11764705882352941,
							1
						],
						"angle": 4.71238898038469,
						"zElevation": 0
					}
				}
			],
			"sid": 924397421412904,
			"effectTypes": [],
			"isInitiallyVisible": true,
			"isInitiallyInteractive": true,
			"isHTMLElementsLayer": false,
			"color": [
				1,
				1,
				1,
				1
			],
			"backgroundColor": [
				1,
				1,
				1,
				1
			],
			"isTransparent": true,
			"parallaxX": 0,
			"parallaxY": 1,
			"scaleRate": 1,
			"forceOwnTexture": false,
			"renderingMode": "3d",
			"drawOrder": "z-order",
			"useRenderCells": false,
			"blendMode": "normal",
			"zElevation": 0,
			"global": false
		},
		{
			"name": "Objects",
			"overriden": 0,
			"subLayers": [],
			"instances": [
				{
					"type": "Ground",
					"properties": {
						"initially-visible": false,
						"initial-animation": "Animation 1",
						"initial-frame": 0,
						"enable-collisions": true,
						"live-preview": false
					},
					"uid": 89,
					"sid": 320104404033097,
					"tags": "",
					"instanceVariables": {},
					"behaviors": {
						"Physics": {
							"properties": {
								"immovable": true,
								"collision-mask": "use-collision-polygon",
								"prevent-rotation": false,
								"density": 1,
								"friction": 0.5,
								"elasticity": 0.2,
								"linear-damping": 0,
								"angular-damping": 0.01,
								"bullet": false,
								"enabled": true
							}
						}
					},
					"showing": true,
					"locked": false,
					"world": {
						"x": 100,
						"y": 928,
						"width": 520,
						"height": 352,
						"originX": 0,
						"originY": 0,
						"color": [
							1,
							1,
							1,
							1
						],
						"angle": 0,
						"zElevation": 0
					}
				},
				{
					"type": "Egg",
					"properties": {
						"initially-visible": true,
						"initial-animation": "Default",
						"initial-frame": 0,
						"enable-collisions": true,
						"live-preview": false
					},
					"uid": 90,
					"sid": 743756529125977,
					"tags": "",
					"instanceVariables": {
						"FaceType": 0
					},
					"behaviors": {
						"Sine": {
							"properties": {
								"movement": "angle",
								"wave": "sine",
								"period": 2.5,
								"period-random": 1.5,
								"period-offset": 0,
								"period-offset-random": 0,
								"magnitude": 3,
								"magnitude-random": 2,
								"enabled": false,
								"live-preview": false
							}
						},
						"Pin": {
							"properties": {
								"destroy": false
							}
						},
						"Physics": {
							"properties": {
								"immovable": true,
								"collision-mask": "use-collision-polygon",
								"prevent-rotation": false,
								"density": 1,
								"friction": 0.5,
								"elasticity": 0.2,
								"linear-damping": 0,
								"angular-damping": 0.01,
								"bullet": false,
								"enabled": true
							}
						}
					},
					"instanceFolderItem": {
						"sid": 743756529125977,
						"expanded": true,
						"folderName": "",
						"indexInFolder": -1,
						"folderNestingLevel": -1
					},
					"showing": true,
					"locked": false,
					"world": {
						"x": 260,
						"y": 924,
						"width": 84,
						"height": 100,
						"originX": 0.5,
						"originY": 1,
						"color": [
							1,
							1,
							1,
							1
						],
						"angle": 0,
						"zElevation": 0
					}
				},
				{
					"type": "Egg",
					"properties": {
						"initially-visible": true,
						"initial-animation": "Default",
						"initial-frame": 0,
						"enable-collisions": true,
						"live-preview": false
					},
					"uid": 151,
					"sid": 916977079341395,
					"tags": "",
					"instanceVariables": {
						"FaceType": 1
					},
					"behaviors": {
						"Sine": {
							"properties": {
								"movement": "angle",
								"wave": "sine",
								"period": 2.5,
								"period-random": 1.5,
								"period-offset": 0,
								"period-offset-random": 0,
								"magnitude": 3,
								"magnitude-random": 2,
								"enabled": false,
								"live-preview": false
							}
						},
						"Pin": {
							"properties": {
								"destroy": false
							}
						},
						"Physics": {
							"properties": {
								"immovable": true,
								"collision-mask": "use-collision-polygon",
								"prevent-rotation": false,
								"density": 1,
								"friction": 0.5,
								"elasticity": 0.2,
								"linear-damping": 0,
								"angular-damping": 0.01,
								"bullet": false,
								"enabled": true
							}
						}
					},
					"instanceFolderItem": {
						"sid": 916977079341395,
						"expanded": true,
						"folderName": "",
						"indexInFolder": -1,
						"folderNestingLevel": -1
					},
					"showing": true,
					"locked": false,
					"world": {
						"x": 460,
						"y": 924,
						"width": 84,
						"height": 100,
						"originX": 0.5,
						"originY": 1,
						"color": [
							1,
							1,
							1,
							1
						],
						"angle": 0,
						"zElevation": 0
					}
				}
			],
			"sid": 575216415708189,
			"effectTypes": [],
			"isInitiallyVisible": true,
			"isInitiallyInteractive": true,
			"isHTMLElementsLayer": false,
			"color": [
				1,
				1,
				1,
				1
			],
			"backgroundColor": [
				1,
				1,
				1,
				1
			],
			"isTransparent": true,
			"parallaxX": 0,
			"parallaxY": 1,
			"scaleRate": 1,
			"forceOwnTexture": false,
			"renderingMode": "3d",
			"drawOrder": "z-order",
			"useRenderCells": false,
			"blendMode": "normal",
			"zElevation": 0,
			"global": false
		},
		{
			"name": "UI",
			"overriden": 0,
			"subLayers": [],
			"instances": [
				{
					"type": "BtnSettings",
					"properties": {
						"initially-visible": true,
						"initial-animation": "Animation 1",
						"initial-frame": 0,
						"enable-collisions": true,
						"live-preview": false
					},
					"uid": 96,
					"sid": 839727073711118,
					"tags": "",
					"instanceVariables": {},
					"behaviors": {
						"Tween": {
							"properties": {
								"enabled": true
							}
						}
					},
					"instanceFolderItem": {
						"sid": 839727073711118,
						"expanded": true,
						"folderName": "",
						"indexInFolder": -1,
						"folderNestingLevel": -1
					},
					"showing": true,
					"locked": false,
					"world": {
						"x": 77,
						"y": 75,
						"width": 94,
						"height": 102,
						"originX": 0.5,
						"originY": 0.47058823529411764,
						"color": [
							1,
							1,
							1,
							1
						],
						"angle": 0,
						"zElevation": 0
					}
				},
				{
					"type": "BtnRestart",
					"properties": {
						"initially-visible": true,
						"initial-animation": "Animation 1",
						"initial-frame": 0,
						"enable-collisions": true,
						"live-preview": false
					},
					"uid": 97,
					"sid": 159516797722964,
					"tags": "",
					"instanceVariables": {},
					"behaviors": {
						"Tween": {
							"properties": {
								"enabled": true
							}
						}
					},
					"instanceFolderItem": {
						"sid": 159516797722964,
						"expanded": true,
						"folderName": "",
						"indexInFolder": -1,
						"folderNestingLevel": -1
					},
					"showing": true,
					"locked": false,
					"world": {
						"x": 643,
						"y": 75,
						"width": 94,
						"height": 102,
						"originX": 0.5,
						"originY": 0.47058823529411764,
						"color": [
							1,
							1,
							1,
							1
						],
						"angle": 0,
						"zElevation": 0
					}
				},
				{
					"type": "BtnHints",
					"properties": {
						"initially-visible": true,
						"initial-animation": "Animation 1",
						"initial-frame": 0,
						"enable-collisions": true,
						"live-preview": false
					},
					"uid": 98,
					"sid": 972580625605758,
					"tags": "",
					"instanceVariables": {},
					"behaviors": {
						"Tween": {
							"properties": {
								"enabled": true
							}
						}
					},
					"instanceFolderItem": {
						"sid": 972580625605758,
						"expanded": true,
						"folderName": "",
						"indexInFolder": -1,
						"folderNestingLevel": -1
					},
					"showing": true,
					"locked": false,
					"world": {
						"x": 250,
						"y": 1135,
						"width": 104,
						"height": 114,
						"originX": 0.5,
						"originY": 0.47368421052631576,
						"color": [
							1,
							1,
							1,
							1
						],
						"angle": 0,
						"zElevation": 0
					}
				},
				{
					"type": "BtnSkip",
					"properties": {
						"initially-visible": true,
						"initial-animation": "Animation 1",
						"initial-frame": 0,
						"enable-collisions": true,
						"live-preview": false
					},
					"uid": 99,
					"sid": 254365547278747,
					"tags": "",
					"instanceVariables": {},
					"behaviors": {
						"Tween": {
							"properties": {
								"enabled": true
							}
						}
					},
					"instanceFolderItem": {
						"sid": 254365547278747,
						"expanded": true,
						"folderName": "",
						"indexInFolder": -1,
						"folderNestingLevel": -1
					},
					"showing": true,
					"locked": false,
					"world": {
						"x": 470,
						"y": 1135,
						"width": 104,
						"height": 114,
						"originX": 0.5,
						"originY": 0.47368421052631576,
						"color": [
							1,
							1,
							1,
							1
						],
						"angle": 0,
						"zElevation": 0
					}
				},
				{
					"type": "LevelTextPanel",
					"properties": {
						"initially-visible": true,
						"initial-animation": "Default",
						"initial-frame": 0,
						"enable-collisions": true,
						"live-preview": false
					},
					"uid": 100,
					"sid": 810575057058001,
					"tags": "",
					"instanceVariables": {},
					"behaviors": {
						"Tween": {
							"properties": {
								"enabled": true
							}
						}
					},
					"instanceFolderItem": {
						"sid": 810575057058001,
						"expanded": true,
						"folderName": "",
						"indexInFolder": -1,
						"folderNestingLevel": -1
					},
					"showing": true,
					"locked": false,
					"world": {
						"x": 360,
						"y": 75,
						"width": 344,
						"height": 78,
						"originX": 0.5,
						"originY": 0.5,
						"color": [
							1,
							1,
							1,
							1
						],
						"angle": 0,
						"zElevation": 0
					}
				},
				{
					"type": "LevelText",
					"properties": {
						"text": "Level",
						"enable-bbcode": true,
						"character-width": 34,
						"character-height": 43,
						"character-set": "0123456789Levl:-",
						"spacing-data": "[[16,\" \"],[13,\"l\"],[14,\":\"],[21,\"1-\"],[28,\"v\"],[29,\"579\"],[30,\"368L\"],[31,\"02e\"],[32,\"4\"]]",
						"scale": 1,
						"character-spacing": -3,
						"line-height": 0,
						"horizontal-alignment": "center",
						"vertical-alignment": "center",
						"wrapping": "word",
						"initially-visible": true,
						"origin": "center",
						"read-aloud": false
					},
					"uid": 101,
					"sid": 461366079948829,
					"tags": "",
					"instanceVariables": {},
					"behaviors": {
						"Tween": {
							"properties": {
								"enabled": true
							}
						}
					},
					"instanceFolderItem": {
						"sid": 461366079948829,
						"expanded": true,
						"folderName": "",
						"indexInFolder": -1,
						"folderNestingLevel": -1
					},
					"showing": true,
					"locked": false,
					"world": {
						"x": 360,
						"y": 75,
						"width": 312,
						"height": 78,
						"originX": 0.5,
						"originY": 0.5,
						"color": [
							1,
							1,
							1,
							1
						],
						"angle": 0,
						"zElevation": 0
					}
				},
				{
					"type": "HintsCounter",
					"properties": {
						"initially-visible": true,
						"initial-animation": "Animation 1",
						"initial-frame": 5,
						"enable-collisions": true,
						"live-preview": false
					},
					"uid": 102,
					"sid": 740061530236036,
					"tags": "",
					"instanceVariables": {},
					"behaviors": {
						"Tween": {
							"properties": {
								"enabled": true
							}
						}
					},
					"instanceFolderItem": {
						"sid": 740061530236036,
						"expanded": true,
						"folderName": "",
						"indexInFolder": -1,
						"folderNestingLevel": -1
					},
					"showing": true,
					"locked": false,
					"world": {
						"x": 288,
						"y": 1191,
						"width": 52,
						"height": 52,
						"originX": 0.5,
						"originY": 0.5,
						"color": [
							1,
							1,
							1,
							1
						],
						"angle": 0,
						"zElevation": 0
					}
				},
				{
					"type": "AdPicture",
					"properties": {
						"initially-visible": true,
						"initial-animation": "Animation 1",
						"initial-frame": 0,
						"enable-collisions": true,
						"live-preview": false
					},
					"uid": 103,
					"sid": 431771555644710,
					"tags": "",
					"instanceVariables": {},
					"behaviors": {
						"Tween": {
							"properties": {
								"enabled": true
							}
						}
					},
					"instanceFolderItem": {
						"sid": 431771555644710,
						"expanded": true,
						"folderName": "",
						"indexInFolder": -1,
						"folderNestingLevel": -1
					},
					"showing": true,
					"locked": false,
					"world": {
						"x": 508,
						"y": 1191,
						"width": 56,
						"height": 50,
						"originX": 0.5,
						"originY": 0.5,
						"color": [
							1,
							1,
							1,
							1
						],
						"angle": 0,
						"zElevation": 0
					}
				}
			],
			"sid": 370714872052803,
			"effectTypes": [],
			"isInitiallyVisible": true,
			"isInitiallyInteractive": true,
			"isHTMLElementsLayer": false,
			"color": [
				1,
				1,
				1,
				1
			],
			"backgroundColor": [
				1,
				1,
				1,
				1
			],
			"isTransparent": true,
			"parallaxX": 0,
			"parallaxY": 1,
			"scaleRate": 1,
			"forceOwnTexture": false,
			"renderingMode": "3d",
			"drawOrder": "z-order",
			"useRenderCells": false,
			"blendMode": "normal",
			"zElevation": 0,
			"global": false
		},
		{
			"name": "Fader",
			"overriden": 0,
			"subLayers": [],
			"instances": [
				{
					"type": "Fader",
					"properties": {
						"initially-visible": true,
						"origin": "center",
						"wrap-horizontal": "repeat",
						"wrap-vertical": "repeat",
						"image-offset-x": 0,
						"image-offset-y": 0,
						"image-scale-x": 1,
						"image-scale-y": 1,
						"image-angle": 0,
						"enable-tile-randomization": false,
						"x-random": 1,
						"y-random": 1,
						"angle-random": 1,
						"blend-margin-x": 0.1,
						"blend-margin-y": 0.1
					},
					"uid": 104,
					"sid": 649659208732419,
					"tags": "",
					"instanceVariables": {},
					"behaviors": {
						"Tween": {
							"properties": {
								"enabled": true
							}
						}
					},
					"instanceFolderItem": {
						"sid": 649659208732419,
						"expanded": true,
						"folderName": "",
						"indexInFolder": -1,
						"folderNestingLevel": -1
					},
					"showing": true,
					"locked": false,
					"world": {
						"x": 360,
						"y": 640,
						"width": 720,
						"height": 1280,
						"originX": 0.5,
						"originY": 0.5,
						"color": [
							1,
							1,
							1,
							1
						],
						"angle": 0,
						"zElevation": 0
					}
				}
			],
			"sid": 354559671642722,
			"effectTypes": [],
			"isInitiallyVisible": true,
			"isInitiallyInteractive": true,
			"isHTMLElementsLayer": false,
			"color": [
				1,
				1,
				1,
				1
			],
			"backgroundColor": [
				0,
				0,
				0,
				1
			],
			"isTransparent": true,
			"parallaxX": 0,
			"parallaxY": 1,
			"scaleRate": 1,
			"forceOwnTexture": false,
			"renderingMode": "3d",
			"drawOrder": "z-order",
			"useRenderCells": false,
			"blendMode": "normal",
			"zElevation": 0,
			"global": false
		}
	],
	"scene-graphs-folder-root": {
		"items": [],
		"subfolders": []
	},
	"sid": 303491394667329,
	"nonworld-instances": [],
	"effectTypes": [],
	"width": 720,
	"height": 1280,
	"unboundedScrolling": false,
	"vpX": 0.5,
	"vpY": 0.5,
	"projection": "perspective",
	"eventSheet": "Game ES"
}